setup.py
amitu/__init__.py
amitu/websocket_client.py
amitu_websocket_client.egg-info/PKG-INFO
amitu_websocket_client.egg-info/SOURCES.txt
amitu_websocket_client.egg-info/dependency_links.txt
amitu_websocket_client.egg-info/namespace_packages.txt
amitu_websocket_client.egg-info/top_level.txt