Metadata-Version: 1.0
Name: amitu-websocket-client
Version: 0.1.0
Summary: Eventlet based websocket client
Home-page: http://github.com/amitu/amitu-websocket-client/
Author: Amit Upadhyay
Author-email: upadhyay@gmail.com
License: BSD
Platform: UNKNOWN
